leosatpy/__init__.py
leosatpy/analyseSatObs.py
leosatpy/calibrateSatObs.py
leosatpy/leosatpy_config.ini
leosatpy/reduceSatObs.py
leosatpy/utils/__init__.py
leosatpy/utils/arguments.py
leosatpy/utils/base_conf.py
leosatpy/utils/dataset.py
leosatpy/utils/photometry.py
leosatpy/utils/satellites.py
leosatpy/utils/select_trail.py
leosatpy/utils/sources.py
leosatpy/utils/tables.py
leosatpy/utils/telescope_conf.py
leosatpy/utils/transformations.py
leosatpy/utils/version.py
leosatpy-0.4.1.dist-info/METADATA
leosatpy-0.4.1.dist-info/WHEEL
leosatpy-0.4.1.dist-info/entry_points.txt
leosatpy-0.4.1.dist-info/top_level.txt
leosatpy-0.4.1.dist-info/RECORD
