Metadata-Version: 2.4
Name: leosatpy
Version: 0.4.1
Summary: LEOSatpy is a highly-automated end-to-end pipeline for the reduction, calibration, and analysis of Low Earth Orbit Satellite observations from various telescopes.
Home-page: http://leosatpy.readthedocs.io/
Download-URL: https://github.com/CLEOsat-group/leosatpy/archive/master.zip
Author: Christian Adam
Author-email: Christian Adam <christian.adam84@gmail.com>
Project-URL: Homepage, http://leosatpy.readthedocs.io/
Project-URL: Download, https://github.com/CLEOsat-group/leosatpy/archive/master.zip
Project-URL: Repository, https://github.com/CLEOsat-group/leosatpy
Keywords: astronomy,satellite,data-analysis,pipeline
Classifier: Development Status :: 3 - Alpha
Classifier: Intended Audience :: Science/Research
Classifier: Topic :: Scientific/Engineering :: Astronomy
Classifier: License :: OSI Approved :: GNU General Public License v3 (GPLv3)
Classifier: Programming Language :: Python :: 3.9
Classifier: Programming Language :: Python :: 3.10
Classifier: Programming Language :: Python :: 3.11
Classifier: Programming Language :: Python :: 3.12
Requires-Python: >=3.9
Requires-Dist: astroalign
Requires-Dist: astropy
Requires-Dist: astroquery
Requires-Dist: ccdproc
Requires-Dist: colorlog
Requires-Dist: ephem
Requires-Dist: fast-histogram
Requires-Dist: geopy
Requires-Dist: inputimeout
Requires-Dist: lmfit
Requires-Dist: matplotlib
Requires-Dist: numpy
Requires-Dist: opencv-python
Requires-Dist: packaging
Requires-Dist: pandas
Requires-Dist: photutils
Requires-Dist: pyorbital
Requires-Dist: PyQt5
Requires-Dist: python-dateutil
Requires-Dist: requests
Requires-Dist: scikit-image
Requires-Dist: scikit-learn
Requires-Dist: scipy
Requires-Dist: setuptools
Dynamic: author
Dynamic: download-url
Dynamic: home-page
Dynamic: requires-python
